pymailkit/__init__.py
pymailkit/auth.py
pymailkit/receiver.py
pymailkit/sender.py
pymailkit-2.0.1.dist-info/licenses/LICENSE
pymailkit-2.0.1.dist-info/METADATA
pymailkit-2.0.1.dist-info/WHEEL
pymailkit-2.0.1.dist-info/top_level.txt
pymailkit-2.0.1.dist-info/RECORD
