Metadata-Version: 2.4
Name: PyMailkit
Version: 2.0.1
Summary: A modern Python library for sending and receiving emails with SMTP and IMAP support
Author-email: Kailas P S <kailaspsudheer@gmail.com>
License: MIT License
Project-URL: Homepage, https://github.com/kailasps/pymailkit
Project-URL: Repository, https://github.com/kailasps/pymailkit.git
Project-URL: Bug Tracker, https://github.com/kailasps/pymailkit/issues
Project-URL: License, https://github.com/kailasps/pymailkit/blob/main/LICENSE
Keywords: email,smtp,imap,mail,email-client,pymail
Classifier: Development Status :: 4 - Beta
Classifier: Intended Audience :: Developers
Classifier: License :: OSI Approved :: MIT License
Classifier: Programming Language :: Python :: 3
Classifier: Programming Language :: Python :: 3.8
Classifier: Programming Language :: Python :: 3.9
Classifier: Programming Language :: Python :: 3.10
Classifier: Programming Language :: Python :: 3.11
Classifier: Topic :: Communications :: Email
Classifier: Topic :: Software Development :: Libraries :: Python Modules
Classifier: Operating System :: OS Independent
Requires-Python: >=3.8
License-File: LICENSE
Dynamic: license-file
